pink_bench/__init__.py
pink_bench/library.py
pink_bench/play_scenario.py
pink_bench/scenario.py
pink_bench/scene.py
pink_bench/utils.py
pink_bench/trajectories/__init__.py
pink_bench/trajectories/back_and_forth_trajectory.py
pink_bench/trajectories/lipm_walking_trajectory.py
pink_bench/trajectories/swing_foot_trajectory.py
pink_bench/trajectories/trajectory.py
pink_bench-0.2.0.dist-info/LICENSE
pink_bench-0.2.0.dist-info/WHEEL
pink_bench-0.2.0.dist-info/METADATA
pink_bench-0.2.0.dist-info/RECORD
